pycsro/__init__.py
pycsro/helper.py
pycsro/io.py
pycsro/main.py
pycsro/neighbor.py
pycsro/sro.py
pycsro-0.1.0.data/data/LICENSE
pycsro-0.1.0.dist-info/AUTHORS.txt
pycsro-0.1.0.dist-info/LICENSE
pycsro-0.1.0.dist-info/METADATA
pycsro-0.1.0.dist-info/WHEEL
pycsro-0.1.0.dist-info/entry_points.txt
pycsro-0.1.0.dist-info/top_level.txt
pycsro-0.1.0.dist-info/RECORD
