Metadata-Version: 2.1
Name: pycsro
Version: 0.1.0
Summary: A python package for CSRO paramater calculation
Home-page: https://github.com/yanglonggroup/pyCSRO
Author: Long Yang
Author-email: long_yang@tongji.edu.cn
Maintainer: Changyuan Li
Maintainer-email: lichangyuan@tongji.edu.cn
Keywords: Chemical short range ordering
Classifier: Programming Language :: Python :: 3
Classifier: License :: OSI Approved :: BSD License
Classifier: Operating System :: OS Independent
Classifier: Topic :: Scientific/Engineering :: Chemistry
Classifier: Topic :: Scientific/Engineering :: Physics
Classifier: Intended Audience :: Science/Research
Requires-Python: >=3.9
License-File: LICENSE
License-File: AUTHORS.txt
